pyfinbus/__init__.py
pyfinbus/api_urls.py
pyfinbus/base.py
pyfinbus/browser.py
pyfinbus/stock.py
pyfinbus-0.0.1.dist-info/METADATA
pyfinbus-0.0.1.dist-info/WHEEL
pyfinbus-0.0.1.dist-info/top_level.txt
pyfinbus-0.0.1.dist-info/RECORD
